<core:FragmentDefinition xmlns="sap.f" xmlns:card="sap.f.cards" xmlns:m="sap.m" xmlns:core="sap.ui.core">
	<!--Microsoft Office skill-->
	<Card class="sapUiMediumMargin" width="auto">
		<header>
			<card:Header title="Microsoft Office" iconSrc="./img/office.png"/>
		</header>
		<content>
			<m:RatingIndicator maxValue="5" value="4" tooltip="Regular with Microsoft Office"/>
		</content>
	</Card>
	<!--G Suite skill-->
	<Card class="sapUiMediumMargin" width="auto">
		<header>
			<card:Header title="G Suite" iconSrc="./img/gsuite.png"/>
		</header>
		<content>
			<m:RatingIndicator maxValue="5" value="4" tooltip="Regular with G Suite"/>
		</content>
	</Card>
	<!--Sylob7 skill-->
	<Card class="sapUiMediumMargin" width="auto">
		<header>
			<card:Header title="Sylob7" iconSrc="./img/sylob7.jpg"/>
		</header>
		<content>
			<m:RatingIndicator maxValue="5" value="3" tooltip="Junior with Sylob7"/>
		</content>
	</Card>
	<!--SolidWorks skill-->
	<Card class="sapUiMediumMargin" width="auto">
		<header>
			<card:Header title="SolidWorks" iconSrc="./img/solidworks.png"/>
		</header>
		<content>
			<m:RatingIndicator maxValue="5" value="3" tooltip="Junior with SolidWorks"/>
		</content>
	</Card>
	<!--Salesforce skill-->
	<Card class="sapUiMediumMargin" width="auto">
		<header>
			<card:Header title="Salesforce" iconSrc="./img/salesforce.png"/>
		</header>
		<content>
			<m:RatingIndicator maxValue="5" value="3" tooltip="Junior with Salesforce"/>
		</content>
	</Card>
	<!--Catia skill-->
	<Card class="sapUiMediumMargin" width="auto">
		<header>
			<card:Header title="Catia" iconSrc="./img/catia.jpg"/>
		</header>
		<content>
			<m:RatingIndicator maxValue="5" value="2" tooltip="Notion with Catia"/>
		</content>
	</Card>
	<!--Adobe Photoshop skill-->
	<Card class="sapUiMediumMargin" width="auto">
		<header>
			<card:Header title="Adobe Photoshop" iconSrc="./img/photoshop.png"/>
		</header>
		<content>
			<m:RatingIndicator maxValue="5" value="2" tooltip="Notion with Adobe Photoshop"/>
		</content>
	</Card>
	<!--Adobe Premiere Pro skill-->
	<Card class="sapUiMediumMargin" width="auto">
		<header>
			<card:Header title="Adobe Premiere Pro" iconSrc="./img/premiere.png"/>
		</header>
		<content>
			<m:RatingIndicator maxValue="5" value="2" tooltip="Notion with Adobe Premiere Pro"/>
		</content>
	</Card>
	<!--Weka skill-->
	<Card class="sapUiMediumMargin" width="auto">
		<header>
			<card:Header title="Weka" iconSrc="./img/weka.jpg"/>
		</header>
		<content>
			<m:RatingIndicator maxValue="5" value="2" tooltip="Notion with Weka"/>
		</content>
	</Card>
	<!--Statistica skill-->
	<Card class="sapUiMediumMargin" width="auto">
		<header>
			<card:Header title="Statistica" iconSrc="./img/statistica.png"/>
		</header>
		<content>
			<m:RatingIndicator maxValue="5" value="2" tooltip="Notion with Statistica"/>
		</content>
	</Card>
	<!--FlexSim skill-->
	<Card class="sapUiMediumMargin" width="auto">
		<header>
			<card:Header title="FlexSim" iconSrc="./img/flexsim.png"/>
		</header>
		<content>
			<m:RatingIndicator maxValue="5" value="1" tooltip="Knowledge on FlexSim"/>
		</content>
	</Card>
	<!--Blender skill-->
	<Card class="sapUiMediumMargin" width="auto">
		<header>
			<card:Header title="Blender" iconSrc="./img/blender.png"/>
		</header>
		<content>
			<m:RatingIndicator maxValue="5" value="1" tooltip="Knowledge on Blender"/>
		</content>
	</Card>
	<!--Unreal skill-->
	<Card class="sapUiMediumMargin" width="auto">
		<header>
			<card:Header title="Unreal Engine" iconSrc="./img/unreal.png"/>
		</header>
		<content>
			<m:RatingIndicator maxValue="5" value="1" tooltip="Knowledge on Unreal Engine"/>
		</content>
	</Card>
</core:FragmentDefinition>